classcli/__init__.py
classcli/clibuilder.py
classcli-0.0.1.dist-info/LICENSE
classcli-0.0.1.dist-info/METADATA
classcli-0.0.1.dist-info/WHEEL
classcli-0.0.1.dist-info/top_level.txt
classcli-0.0.1.dist-info/RECORD
