Metadata-Version: 2.1
Name: classcli
Version: 0.0.1
Summary: Command Line Interfaces from custom classes
Home-page: https://github.com/Hrabal/ClassCLI
Author: Federico Cerchiari
Author-email: federicocerchiari@gmail.com
License: APACHE 2.0
Download-URL: https://github.com/Hrabal/ClassCLI/archive/0.0.1.tar.gz
Keywords: python3,cli,argparse,userio,io
Platform: UNKNOWN
Requires-Python: >=3.3
